scripts/__init__.py
scripts/_shell2_cli_menu.py
scripts/shell2_cli.py
scripts/shell2_cli_live.py
scripts/shell2_cli_menu.py
scripts/shell2_debug.py
shell2_cli-0.1.dist-info/METADATA
shell2_cli-0.1.dist-info/WHEEL
shell2_cli-0.1.dist-info/entry_points.txt
shell2_cli-0.1.dist-info/top_level.txt
shell2_cli-0.1.dist-info/RECORD
